iconatron/__init__.py
iconatron/apps.py
iconatron/functions.py
iconatron/templatetags/__init__.py
iconatron/templatetags/iconatron.py
iconatron/templatetags/icons/Archive.svg
iconatron/templatetags/icons/ArchiveFill.svg
iconatron/templatetags/icons/ArrowDown.svg
iconatron/templatetags/icons/ArrowDownFill.svg
iconatron/templatetags/icons/ArrowLeft.svg
iconatron/templatetags/icons/ArrowLeftFill.svg
iconatron/templatetags/icons/ArrowRight.svg
iconatron/templatetags/icons/ArrowRightFill.svg
iconatron/templatetags/icons/ArrowUp.svg
iconatron/templatetags/icons/ArrowUpFill.svg
iconatron/templatetags/icons/Bag.svg
iconatron/templatetags/icons/Bell.svg
iconatron/templatetags/icons/BellFill.svg
iconatron/templatetags/icons/Bookmark.svg
iconatron/templatetags/icons/BookmarkCheck.svg
iconatron/templatetags/icons/BookmarkFill.svg
iconatron/templatetags/icons/BookmarkPlus.svg
iconatron/templatetags/icons/Cart.svg
iconatron/templatetags/icons/CartCheck.svg
iconatron/templatetags/icons/CartMinus.svg
iconatron/templatetags/icons/CartPlus.svg
iconatron/templatetags/icons/Chat.svg
iconatron/templatetags/icons/Chat2.svg
iconatron/templatetags/icons/Chat2Fill.svg
iconatron/templatetags/icons/ChatFill.svg
iconatron/templatetags/icons/Check.svg
iconatron/templatetags/icons/CheckCircle.svg
iconatron/templatetags/icons/CheckCircleFill.svg
iconatron/templatetags/icons/Clock.svg
iconatron/templatetags/icons/ClockFill.svg
iconatron/templatetags/icons/Close.svg
iconatron/templatetags/icons/CloseFill.svg
iconatron/templatetags/icons/Cloud.svg
iconatron/templatetags/icons/CloudDownload.svg
iconatron/templatetags/icons/CloudFill.svg
iconatron/templatetags/icons/Code.svg
iconatron/templatetags/icons/Display.svg
iconatron/templatetags/icons/Down.svg
iconatron/templatetags/icons/Download.svg
iconatron/templatetags/icons/Exit.svg
iconatron/templatetags/icons/Filters.svg
iconatron/templatetags/icons/Filters2.svg
iconatron/templatetags/icons/Gmail.svg
iconatron/templatetags/icons/History.svg
iconatron-0.1.6.dist-info/LICENSE.txt
iconatron-0.1.6.dist-info/METADATA
iconatron-0.1.6.dist-info/WHEEL
iconatron-0.1.6.dist-info/top_level.txt
iconatron-0.1.6.dist-info/RECORD
