Metadata-Version: 2.1
Name: iconatron
Version: 0.1.6
Summary: icons package for django
Home-page: https://github.com/MichailZh/Iconatron.git
Author: MichailZh
Author-email: michail.zhukov@gmail.com
License: MIT
Download-URL: https://github.com/MichailZh/Iconatron/archive/V_03.tar.gz
Keywords: ICONS,DJANGO
Platform: UNKNOWN
Classifier: Development Status :: 3 - Alpha
Classifier: Intended Audience :: Developers
Classifier: Topic :: Software Development :: Build Tools
Classifier: License :: OSI Approved :: MIT License
Classifier: Programming Language :: Python :: 3.8
